kivy_hot_tile_package/__init__.py
kivy_hot_tile_package/hot_tile.kv
kivy_hot_tile_package/main.py
kivy_hot_tile_package-1.1.dist-info/LICENSE
kivy_hot_tile_package-1.1.dist-info/METADATA
kivy_hot_tile_package-1.1.dist-info/WHEEL
kivy_hot_tile_package-1.1.dist-info/entry_points.txt
kivy_hot_tile_package-1.1.dist-info/top_level.txt
kivy_hot_tile_package-1.1.dist-info/RECORD
